terraformgraph/__init__.py
terraformgraph/__main__.py
terraformgraph/aggregator.py
terraformgraph/config_loader.py
terraformgraph/icons.py
terraformgraph/layout.py
terraformgraph/main.py
terraformgraph/parser.py
terraformgraph/renderer.py
terraformgraph/config/aggregation_rules.yaml
terraformgraph/config/logical_connections.yaml
terraformgraph-1.0.3.dist-info/licenses/LICENSE
terraformgraph-1.0.3.dist-info/METADATA
terraformgraph-1.0.3.dist-info/WHEEL
terraformgraph-1.0.3.dist-info/entry_points.txt
terraformgraph-1.0.3.dist-info/top_level.txt
terraformgraph-1.0.3.dist-info/RECORD
