Metadata-Version: 2.4
Name: terraformgraph
Version: 1.0.3
Summary: Generate interactive architecture diagrams from Terraform configurations
Author-email: Ferdinando Bonsegna <1bonsegnaferdinando@gmail.com>
License: MIT
Project-URL: Homepage, https://github.com/ferdinandobons/terraformgraph
Project-URL: Documentation, https://github.com/ferdinandobons/terraformgraph#readme
Project-URL: Repository, https://github.com/ferdinandobons/terraformgraph.git
Project-URL: Issues, https://github.com/ferdinandobons/terraformgraph/issues
Keywords: terraform,infrastructure,diagram,aws,visualization,architecture,terraformgraph
Classifier: Development Status :: 4 - Beta
Classifier: Environment :: Console
Classifier: Intended Audience :: Developers
Classifier: Intended Audience :: System Administrators
Classifier: License :: OSI Approved :: MIT License
Classifier: Operating System :: OS Independent
Classifier: Programming Language :: Python :: 3
Classifier: Programming Language :: Python :: 3.9
Classifier: Programming Language :: Python :: 3.10
Classifier: Programming Language :: Python :: 3.11
Classifier: Programming Language :: Python :: 3.12
Classifier: Topic :: Software Development :: Documentation
Classifier: Topic :: System :: Systems Administration
Requires-Python: >=3.9
License-File: LICENSE
Requires-Dist: python-hcl2>=4.3.0
Requires-Dist: PyYAML>=6.0
Provides-Extra: dev
Requires-Dist: pytest>=7.0; extra == "dev"
Requires-Dist: pytest-cov>=4.0; extra == "dev"
Requires-Dist: black>=23.0; extra == "dev"
Requires-Dist: ruff>=0.1.0; extra == "dev"
Requires-Dist: mypy>=1.0; extra == "dev"
Requires-Dist: types-PyYAML>=6.0; extra == "dev"
Dynamic: license-file
